pymes/__init__.py
pymes/client.py
pymes/exceptions.py
pymes/message.py
pymes_api-0.1.1.dist-info/METADATA
pymes_api-0.1.1.dist-info/WHEEL
pymes_api-0.1.1.dist-info/top_level.txt
pymes_api-0.1.1.dist-info/RECORD
