Metadata-Version: 2.4
Name: pymes-api
Version: 0.1.1
Summary: A Python library for Facebook Messenger API
Author-email: Mohin Uddin Shipon <sshiponuddin22@gmail.com>
Project-URL: Homepage, https://github.com/ssshiponu/pymes
Classifier: Programming Language :: Python :: 3
Classifier: License :: OSI Approved :: MIT License
Classifier: Operating System :: OS Independent
Requires-Python: >=3.7
Requires-Dist: requests
